[{"rType":"asset","rSubType":"image","fileName":"Servicios-43.png","fileSize":127511,"val":"mc-09a5ace454ada8afc529c0afbe1bb952.png","aid":"YYIfFU9Im","size":127511},{"rType":"asset","rSubType":"image","fileName":"TexturaNegra_720.png","fileSize":94812,"val":"mc-03938f5f1e2717618ddf67c8dcd1e1ad.png","aid":"sfepGPoSDQE","size":94812},{"rType":"asset","rSubType":"image","fileName":"Pagina web -08.png","fileSize":645387,"val":"mc-df2c24f39e113dfd427d74f3d1a11baa.png","aid":"YsC8Igt0J","size":645387},{"rType":"asset","rSubType":"image","fileName":"Pagina web -11.png","fileSize":189911,"val":"mc-9bd304b79a6b45db0e2080665400df7d.png","aid":"dr8q2lo4b","size":189911},{"rType":"asset","rSubType":"image","fileName":"Servicios-44.png","fileSize":182658,"val":"mc-7fdf4e88f821de3180e0c3187c950f02.png","aid":"GbX1k7YaQ","size":182658},{"rType":"asset","rSubType":"image","fileName":"Servicios-44.png","fileSize":182658,"val":"mc-7fdf4e88f821de3180e0c3187c950f02.png","aid":"DkfhShGUL","size":182658},{"rType":"asset","rSubType":"image","fileName":"TexturaNegra_720.png","fileSize":94812,"val":"mc-03938f5f1e2717618ddf67c8dcd1e1ad.png","aid":"8xceTg61Pra","size":94812},{"rType":"asset","rSubType":"image","fileName":"TexturaNegra_720.png","fileSize":94812,"val":"mc-03938f5f1e2717618ddf67c8dcd1e1ad.png","aid":"eMQOOimmnsd","size":94812},{"rType":"asset","rSubType":"image","fileName":"TexturaNegra_720.png","fileSize":94812,"val":"mc-03938f5f1e2717618ddf67c8dcd1e1ad.png","aid":"FwaL6I84GB","size":94812},{"rType":"asset","rSubType":"image","fileName":"Servicios-45.png","fileSize":156792,"val":"mc-a79b52ae28326280c6932dc250fe94b5.png","aid":"XjH1sEvWq","size":156792},{"rType":"asset","rSubType":"image","fileName":"Pagina web -02.png","fileSize":635089,"val":"mc-647aec54b215c11af36cfbaaa2ea4a5a.png","aid":"xVCT3br9s","size":635089},{"rType":"asset","rSubType":"image","fileName":"Pagina web -12.png","fileSize":80725,"val":"mc-43a63da50d4d762df3d87969264fbd00.png","aid":"IFTKEnCxi","size":80725},{"rType":"asset","rSubType":"image","fileName":"Pagina web _Mesa de trabajo 1.png","fileSize":1107311,"val":"mc-e825bb3f064410bf2596cb368ec9c505.png","aid":"M9GTSX03m","size":1107311},{"rType":"asset","rSubType":"image","fileName":"Pagina web -12.png","fileSize":80725,"val":"mc-43a63da50d4d762df3d87969264fbd00.png","aid":"Jv7wl3Qt4","size":80725},{"rType":"asset","rSubType":"image","fileName":"Pagina web -25.png","fileSize":14053,"val":"mc-257c64f42a08c1305a034c2c6bf28433.png","aid":"STuQ_hN26","size":14053},{"rType":"asset","rSubType":"image","fileName":"Servicios-45.png","fileSize":156792,"val":"mc-a79b52ae28326280c6932dc250fe94b5.png","aid":"ZJVF7xFaV","size":156792},{"rType":"asset","rSubType":"image","fileName":"Pagina web -12.png","fileSize":80725,"val":"mc-43a63da50d4d762df3d87969264fbd00.png","aid":"VerTA-Rgc","size":80725},{"rType":"asset","rSubType":"image","fileName":"Pagina web -12.png","fileSize":80725,"val":"mc-43a63da50d4d762df3d87969264fbd00.png","aid":"3aCkrz6cd","size":80725},{"rType":"asset","rSubType":"image","fileName":"Servicios-43.png","fileSize":127511,"val":"mc-09a5ace454ada8afc529c0afbe1bb952.png","aid":"dHWFE-P-M","size":127511},{"rType":"asset","rSubType":"image","fileName":"Pagina web -25.png","fileSize":14053,"val":"mc-257c64f42a08c1305a034c2c6bf28433.png","aid":"zBFlBk1o-","size":14053},{"rType":"asset","rSubType":"image","fileName":"Pagina web -09.png","fileSize":161831,"val":"mc-343998b53b00686736d3f29309f03ce0.png","aid":"JsFumwLHb","size":161831}]